setup.cfg
setup.py
samtools_metrics_sqlite/__init__.py
samtools_metrics_sqlite/__main__.py
samtools_metrics_sqlite/main.py
samtools_metrics_sqlite.egg-info/PKG-INFO
samtools_metrics_sqlite.egg-info/SOURCES.txt
samtools_metrics_sqlite.egg-info/dependency_links.txt
samtools_metrics_sqlite.egg-info/entry_points.txt
samtools_metrics_sqlite.egg-info/requires.txt
samtools_metrics_sqlite.egg-info/top_level.txt
samtools_metrics_sqlite/metrics/__init__.py
samtools_metrics_sqlite/metrics/samtools_flagstat.py
samtools_metrics_sqlite/metrics/samtools_idxstats.py
samtools_metrics_sqlite/metrics/samtools_stats.py