Metadata-Version: 1.1
Name: samtools-metrics-sqlite
Version: 0.6
Summary: store samtools metrics in sqlite
Home-page: https://github.com/jeremiahsavage/samtools_metrics_sqlite
Author: Jeremiah H. Savage
Author-email: jeremiahsavage@gmail.com
License: Apache 2.0
Platform: UNKNOWN
Classifier: Development Status :: 3 - Alpha
Classifier: Intended Audience :: Developers
Classifier: License :: OSI Approved :: Apache Software License
Classifier: Programming Language :: Python
Classifier: Programming Language :: Python :: 2
Classifier: Programming Language :: Python :: 3
